cactus/__init__.py
cactus/browser.py
cactus/cli.py
cactus/exceptions.py
cactus/logger.py
cactus/mime.py
cactus/page.py
cactus/server.py
cactus/site.py
cactus/template_tags.py
cactus/ui.py
cactus/bootstrap/__init__.py
cactus/bootstrap/archive.py
cactus/bootstrap/package.py
cactus/compat/__init__.py
cactus/compat/page.py
cactus/compat/paths.py
cactus/config/__init__.py
cactus/config/fallback.py
cactus/config/file.py
cactus/config/router.py
cactus/contrib/__init__.py
cactus/contrib/external/__init__.py
cactus/contrib/external/closure.py
cactus/contrib/external/yui.py
cactus/i18n/__init__.py
cactus/i18n/commands.py
cactus/listener/__init__.py
cactus/listener/mac.py
cactus/listener/polling.py
cactus/plugin/__init__.py
cactus/plugin/defaults.py
cactus/plugin/loader.py
cactus/plugin/manager.py
cactus/plugin/builtin/__init__.py
cactus/plugin/builtin/cache.py
cactus/plugin/builtin/context.py
cactus/plugin/builtin/ignore.py
cactus/skeleton/README.md
cactus/skeleton/config.json
cactus/skeleton/.github/workflows/github-pages.yml
cactus/skeleton/locale/README.md
cactus/skeleton/pages/about.html
cactus/skeleton/pages/contact.html
cactus/skeleton/pages/error.html
cactus/skeleton/pages/index.html
cactus/skeleton/pages/robots.txt
cactus/skeleton/pages/sitemap.xml
cactus/skeleton/plugins/__init__.py
cactus/skeleton/plugins/blog.disabled.py
cactus/skeleton/plugins/coffeescript.disabled.py
cactus/skeleton/plugins/gitcommitid.disabled.py
cactus/skeleton/plugins/haml.disabled.py
cactus/skeleton/plugins/page_context.py
cactus/skeleton/plugins/sass.disabled.py
cactus/skeleton/plugins/scss.disabled.py
cactus/skeleton/plugins/sprites.disabled.py
cactus/skeleton/plugins/static_optimizers.py
cactus/skeleton/static/css/bootstrap.css
cactus/skeleton/static/fonts/glyphicons-halflings-regular.eot
cactus/skeleton/static/fonts/glyphicons-halflings-regular.svg
cactus/skeleton/static/fonts/glyphicons-halflings-regular.ttf
cactus/skeleton/static/fonts/glyphicons-halflings-regular.woff
lava_cactus-3.0.0.dist-info/AUTHORS
lava_cactus-3.0.0.dist-info/LICENSE
lava_cactus-3.0.0.dist-info/METADATA
lava_cactus-3.0.0.dist-info/WHEEL
lava_cactus-3.0.0.dist-info/entry_points.txt
lava_cactus-3.0.0.dist-info/top_level.txt
lava_cactus-3.0.0.dist-info/RECORD
