Metadata-Version: 2.2
Name: lava-cactus
Version: 3.0.0
Summary: Static site generation and deployment.
Home-page: https://github.com/quillcraftsman/lavacactus
Author: quillcraftsman
Author-email: quill@craftsman.lol
License: BSD
Project-URL: Documentation, https://github.com/quillcraftsman/lavacactus
Project-URL: Source, https://github.com/quillcraftsman/lavacactus
Project-URL: Tracker, https://github.com/quillcraftsman/lavacactus/issues
Project-URL: Release notes, https://github.com/quillcraftsman/lavacactus/releases
Project-URL: Changelog, https://github.com/quillcraftsman/lavacactus/releases
Project-URL: Download, https://pypi.org/project/lava-cactus/
Classifier: Development Status :: 5 - Production/Stable
Classifier: Environment :: Console
Classifier: Intended Audience :: Developers
Classifier: License :: OSI Approved :: BSD License
Classifier: Natural Language :: English
Classifier: Programming Language :: Python
Classifier: Programming Language :: Python :: 3
Classifier: Programming Language :: Python :: 3.10
Classifier: Programming Language :: Python :: 3.11
Classifier: Programming Language :: Python :: 3.12
Classifier: Topic :: Internet :: WWW/HTTP
Classifier: Operating System :: OS Independent
License-File: LICENSE
License-File: AUTHORS
Requires-Dist: Django==5.1.1
Requires-Dist: markdown2==2.4.10
Requires-Dist: keyring==24.2.0
Requires-Dist: boto==2.49.0
Requires-Dist: tornado==6.3.3
Requires-Dist: colorlog==6.7.0
Requires-Dist: colorama==0.4.6
Requires-Dist: six==1.16.0
Requires-Dist: PyYAML==6.0.1
Requires-Dist: setuptools==75.1.0
Dynamic: author
Dynamic: author-email
Dynamic: classifier
Dynamic: description
Dynamic: description-content-type
Dynamic: home-page
Dynamic: license
Dynamic: project-url
Dynamic: requires-dist
Dynamic: summary
